MANIFEST.in
conftest.py
setup.cfg
setup.py
test.py
zeronimo/__about__.py
zeronimo/__init__.py
zeronimo/application.py
zeronimo/core.py
zeronimo/exceptions.py
zeronimo/helpers.py
zeronimo/messaging.py
zeronimo/results.py
zeronimo.egg-info/PKG-INFO
zeronimo.egg-info/SOURCES.txt
zeronimo.egg-info/dependency_links.txt
zeronimo.egg-info/requires.txt
zeronimo.egg-info/top_level.txt