Metadata-Version: 1.1
Name: zeronimo
Version: 0.3.0
Summary: RPC between distributed workers
Home-page: http://github.com/sublee/zeronimo/
Author: Heungsub Lee
Author-email: sub@subl.ee
License: BSD
Platform: any
Classifier: Development Status :: 1 - Planning
Classifier: Intended Audience :: Developers
Classifier: License :: OSI Approved :: BSD License
Classifier: Operating System :: OS Independent
Classifier: Programming Language :: Python
Classifier: Programming Language :: Python :: 2
Classifier: Programming Language :: Python :: 2.7
Classifier: Programming Language :: Python :: Implementation :: CPython
Classifier: Topic :: Software Development
